decorworld_database_model/__init__.py
decorworld_database_model/alembic/env.py
decorworld_database_model/alembic/README
decorworld_database_model/alembic/script.py.mako
decorworld_database_model/alembic/versions/082d80622e74_create_order_item_table.py
decorworld_database_model/alembic/versions/0f47592c12ce_add_paid_status_for_order.py
decorworld_database_model/alembic/versions/13a3b750c40e_add_pre_order_and_discount_columns_to_.py
decorworld_database_model/alembic/versions/143be2620e05_rename_preorder_column_in_products_table.py
decorworld_database_model/alembic/versions/1f52b78d99b5_add_page_images_table.py
decorworld_database_model/alembic/versions/21550951e198_drop_discounts_table.py
decorworld_database_model/alembic/versions/26cdf6a5af2b_change_discount_type_to_integer_from_.py
decorworld_database_model/alembic/versions/28e24bf5b755_create_user_table.py
decorworld_database_model/alembic/versions/3afcf5045272_create_favorite_table.py
decorworld_database_model/alembic/versions/41640c6fbc41_create_product_table.py
decorworld_database_model/alembic/versions/432183be6e50_add_role_column_to_user_table.py
decorworld_database_model/alembic/versions/437ce57390c5_remove_active_discount_column_and_.py
decorworld_database_model/alembic/versions/46fe20e7d2c8_add_reviews_table.py
decorworld_database_model/alembic/versions/4cfd3fc062af_add_date_column_to_review.py
decorworld_database_model/alembic/versions/556ff2c83f9f_create_order_table.py
decorworld_database_model/alembic/versions/57c6c9633e32_create_shipping_method_table.py
decorworld_database_model/alembic/versions/6787273bd08d_create_image_table.py
decorworld_database_model/alembic/versions/68b8e7a46dc0_add_contact_columns_to_order_table.py
decorworld_database_model/alembic/versions/72c749f78b2c_add_registratrion_activation_and_update_.py
decorworld_database_model/alembic/versions/7561a3637af6_create_discount_table.py
decorworld_database_model/alembic/versions/76e56ad9a0d6_add_active_column_to_users_table.py
decorworld_database_model-0.6.9.dist-info/METADATA
decorworld_database_model-0.6.9.dist-info/WHEEL
decorworld_database_model-0.6.9.dist-info/RECORD
