Metadata-Version: 2.1
Name: decorworld-database-model
Version: 0.6.9
Summary: Database models for DecorWorld
Author: Pintér Tamás
Author-email: tamas.pinter@pannonszoftver.hu
Requires-Python: >=3.8,<4.0
Classifier: Programming Language :: Python :: 3
Classifier: Programming Language :: Python :: 3.8
Classifier: Programming Language :: Python :: 3.9
Classifier: Programming Language :: Python :: 3.10
Classifier: Programming Language :: Python :: 3.11
Requires-Dist: marshmallow (==3.14.1)
Requires-Dist: sqlalchemy (==1.3.18)
